prodvana/__init__.py
prodvana/client.py
prodvana/proto/__init__.py
prodvana/proto/prodvana/__init__.py
prodvana/proto/prodvana/agent/__init__.py
prodvana/proto/prodvana/agent/agent_interaction_pb2.py
prodvana/proto/prodvana/agent/agent_interaction_pb2.pyi
prodvana/proto/prodvana/agent/agent_interaction_pb2_grpc.py
prodvana/proto/prodvana/agent/agent_interaction_pb2_grpc.pyi
prodvana/proto/prodvana/application/__init__.py
prodvana/proto/prodvana/application/application_config_pb2.py
prodvana/proto/prodvana/application/application_config_pb2.pyi
prodvana/proto/prodvana/application/application_config_pb2_grpc.py
prodvana/proto/prodvana/application/application_config_pb2_grpc.pyi
prodvana/proto/prodvana/application/application_manager_pb2.py
prodvana/proto/prodvana/application/application_manager_pb2.pyi
prodvana/proto/prodvana/application/application_manager_pb2_grpc.py
prodvana/proto/prodvana/application/application_manager_pb2_grpc.pyi
prodvana/proto/prodvana/application/object_pb2.py
prodvana/proto/prodvana/application/object_pb2.pyi
prodvana/proto/prodvana/application/object_pb2_grpc.py
prodvana/proto/prodvana/application/object_pb2_grpc.pyi
prodvana/proto/prodvana/application/user_metadata_pb2.py
prodvana/proto/prodvana/application/user_metadata_pb2.pyi
prodvana/proto/prodvana/application/user_metadata_pb2_grpc.py
prodvana/proto/prodvana/application/user_metadata_pb2_grpc.pyi
prodvana/proto/prodvana/async_task/__init__.py
prodvana/proto/prodvana/async_task/task_metadata_pb2.py
prodvana/proto/prodvana/async_task/task_metadata_pb2.pyi
prodvana/proto/prodvana/async_task/task_metadata_pb2_grpc.py
prodvana/proto/prodvana/async_task/task_metadata_pb2_grpc.pyi
prodvana/proto/prodvana/auth/__init__.py
prodvana/proto/prodvana/auth/auth_manager_pb2.py
prodvana/proto/prodvana/auth/auth_manager_pb2.pyi
prodvana/proto/prodvana/auth/auth_manager_pb2_grpc.py
prodvana/proto/prodvana/auth/auth_manager_pb2_grpc.pyi
prodvana/proto/prodvana/auth/auth_pb2.py
prodvana-0.3.49.dist-info/METADATA
prodvana-0.3.49.dist-info/WHEEL
prodvana-0.3.49.dist-info/RECORD
