Metadata-Version: 2.1
Name: prodvana
Version: 0.3.49
Summary: Prodvana's client libraries
Home-page: https://prodvana.io
Requires-Python: >=3.10,<4.0
Classifier: Programming Language :: Python :: 3
Classifier: Programming Language :: Python :: 3.10
Classifier: Programming Language :: Python :: 3.11
Requires-Dist: google-api-python-client (>=2.58.0,<3.0)
Requires-Dist: grpc-interceptor (>=0.15.0,<0.16.0)
Requires-Dist: grpc-stubs (>=1.24.0,<2.0)
Requires-Dist: grpcio (>=1.48.0,<2.0)
Requires-Dist: protobuf (>=4.21.0,<5.0)
Requires-Dist: types-protobuf (>=3.20.0,<5.0)
Project-URL: Documentation, https://docs.prodvana.io
Project-URL: Repository, https://github.com/prodvana/prodvana-public
